lazynet-0.6.0.dist-info/METADATA
lazynet-0.6.0.dist-info/WHEEL
lazynet-0.6.0.dist-info/licenses/LICENSE
lazynet.libs/libgcc_s-39080030.so.1
lazynet/__init__.py
lazynet/_lazynet.cpython-312-aarch64-linux-musl.so
lazynet/ex_timer.py
lazynet-0.6.0.dist-info/RECORD
