Metadata-Version: 2.4
Name: lazynet
Version: 0.6.0
Classifier: Development Status :: 4 - Beta
Classifier: Intended Audience :: Developers
Classifier: License :: OSI Approved :: MIT License
Classifier: Operating System :: OS Independent
Classifier: Programming Language :: Rust
Classifier: Programming Language :: Python :: Implementation :: CPython
Classifier: Programming Language :: Python :: 3
Classifier: Programming Language :: Python :: 3.10
Classifier: Programming Language :: Python :: 3.11
Classifier: Programming Language :: Python :: 3.12
Classifier: Programming Language :: Python :: 3.13
Classifier: Topic :: Internet :: WWW/HTTP
Classifier: Topic :: Software Development :: Libraries :: Python Modules
License-File: LICENSE
Summary: Lazy-evaluated, asynchronous HTTP requests powered by Rust
Keywords: http,async,lazy,requests,concurrent,rust,pyo3
Author-email: Joe Nap <joenap@gmail.com>
License: MIT
Requires-Python: >=3.10
Project-URL: Homepage, https://github.com/joenap/lazynet
Project-URL: Repository, https://github.com/joenap/lazynet
Project-URL: Changelog, https://github.com/joenap/lazynet/blob/master/CHANGELOG.md
Project-URL: Issues, https://github.com/joenap/lazynet/issues
